pytx/__init__.py
pytx/common.py
pytx/errors.py
pytx/init.py
pytx/malware.py
pytx/request.py
pytx/threat_exchange_member.py
pytx/threat_indicator.py
pytx/vocabulary.py
pytx-0.1.3.data/scripts/get_compromised_credentials.py
pytx-0.1.3.data/scripts/get_indicators.py
pytx-0.1.3.data/scripts/get_members.py
pytx-0.1.3.data/scripts/malware_api.py
pytx-0.1.3.data/scripts/malware_grabber.py
pytx-0.1.3.dist-info/DESCRIPTION.rst
pytx-0.1.3.dist-info/METADATA
pytx-0.1.3.dist-info/metadata.json
pytx-0.1.3.dist-info/RECORD
pytx-0.1.3.dist-info/top_level.txt
pytx-0.1.3.dist-info/WHEEL
