Metadata-Version: 2.0
Name: pytx
Version: 0.1.3
Summary: Python Library for Facebook ThreatExchange
Home-page: https://www.github.com/facebook/ThreatExchange
Author: Mike Goffin
Author-email: mgoffin@gmail.com
License: BSD
Keywords: facebook threatexchange
Platform: UNKNOWN
Classifier: Development Status :: 3 - Alpha
Classifier: Intended Audience :: Developers
Classifier: Topic :: Software Development :: Build Tools
Classifier: License :: OSI Approved :: BSD License
Classifier: Programming Language :: Python :: 2.7
Requires-Dist: requests
